[{"constant":false,"inputs":[],"name":"gem","outputs":[{"name":"","type":"address"}],"payable":false,"stateMutability":"nonpayable","type":"function"},{"constant":false,"inputs":[{"name":"","type":"bytes32"},{"name":"","type":"uint256"}],"name":"join","outputs":[],"payable":true,"stateMutability":"payable","type":"function"},{"constant":false,"inputs":[{"name":"","type":"address"},{"name":"","type":"uint256"}],"name":"exit","outputs":[],"payable":false,"stateMutability":"nonpayable","type":"function"}]