[{"constant":true,"inputs":[{"name":"","type":"address"}],"name":"orcl","outputs":[{"name":"","type":"bool"}],"payable":false,"stateMutability":"view","type":"function"},{"constant":false,"inputs":[{"name":"owner_","type":"address"}],"name":"setOwner","outputs":[],"payable":false,"stateMutability":"nonpayable","type":"function"},{"constant":true,"inputs":[],"name":"age","outputs":[{"name":"","type":"uint256"}],"payable":false,"stateMutability":"view","type":"function"},{"constant":false,"inputs":[{"name":"a","type":"address"}],"name":"lift","outputs":[],"payable":false,"stateMutability":"nonpayable","type":"function"},{"constant":true,"inputs":[],"name":"val","outputs":[{"name":"","type":"uint256"}],"payable":false,"stateMutability":"view","type":"function"},{"constant":false,"inputs":[{"name":"min_","type":"uint256"}],"name":"setMin","outputs":[],"payable":false,"stateMutability":"nonpayable","type":"function"},{"constant":true,"inputs":[],"name":"wat","outputs":[{"name":"","type":"bytes32"}],"payable":false,"stateMutability":"view","type":"function"},{"constant":true,"inputs":[],"name":"read","outputs":[{"name":"","type":"bytes32"}],"payable":false,"stateMutability":"view","type":"function"},{"constant":true,"inputs":[],"name":"peek","outputs":[{"name":"","type":"bytes32"},{"name":"","type":"bool"}],"payable":false,"stateMutability":"view","type":"function"},{"constant":false,"inputs":[{"name":"authority_","type":"address"}],"name":"setAuthority","outputs":[],"payable":false,"stateMutability":"nonpayable","type":"function"},{"constant":false,"inputs":[{"name":"val_","type":"uint256[]"},{"name":"age_","type":"uint256[]"},{"name":"v","type":"uint8[]"},{"name":"r","type":"bytes32[]"},{"name":"s","type":"bytes32[]"}],"name":"poke","outputs":[],"payable":false,"stateMutability":"nonpayable","type":"function"},{"constant":true,"inputs":[],"name":"owner","outputs":[{"name":"","type":"address"}],"payable":false,"stateMutability":"view","type":"function"},{"constant":false,"inputs":[{"name":"a","type":"address"}],"name":"drop","outputs":[],"payable":false,"stateMutability":"nonpayable","type":"function"},{"constant":true,"inputs":[],"name":"authority","outputs":[{"name":"","type":"address"}],"payable":false,"stateMutability":"view","type":"function"},{"constant":true,"inputs":[],"name":"min","outputs":[{"name":"","type":"uint256"}],"payable":false,"stateMutability":"view","type":"function"},{"inputs":[{"name":"_wat","type":"bytes32"}],"payable":false,"stateMutability":"nonpayable","type":"constructor"},{"anonymous":false,"inputs":[{"indexed":true,"name":"who","type":"address"},{"indexed":false,"name":"val","type":"uint256"},{"indexed":false,"name":"age","type":"uint256"}],"name":"LogFeedPrice","type":"event"},{"anonymous":false,"inputs":[{"indexed":false,"name":"val","type":"uint256"},{"indexed":false,"name":"age","type":"uint256"}],"name":"LogMedianPrice","type":"event"},{"anonymous":false,"inputs":[{"indexed":true,"name":"authority","type":"address"}],"name":"LogSetAuthority","type":"event"},{"anonymous":false,"inputs":[{"indexed":true,"name":"owner","type":"address"}],"name":"LogSetOwner","type":"event"}]